materialx_baker/__init__.py
materialx_baker/exceptions.py
materialx_baker/mtlx_baker.py
materialx_baker/py.typed
materialx_baker/test_mtlx_baker.py
materialx_baker/test_data/blood_red.mtlx
materialx_baker/test_data/invalid.mtlx
materialx_baker/test_data/marbel.mtlx
materialx_baker-0.1.9.dist-info/METADATA
materialx_baker-0.1.9.dist-info/WHEEL
materialx_baker-0.1.9.dist-info/licenses/LICENSE.txt
materialx_baker-0.1.9.dist-info/RECORD
