Metadata-Version: 2.4
Name: materialx-baker
Version: 0.1.9
Summary: A small module for baking textures from MaterialX (.mtlx) format.
Project-URL: Repository, https://github.com/KidziaK/materialx-baker
Author-email: Mikolaj Kida <kida.miko@gmail.com>
License-File: LICENSE.txt
Requires-Python: >=3.11
Requires-Dist: materialx>=1.39.1
Requires-Dist: numpy>=1.24.0
Requires-Dist: openexr>=3.3.2
Requires-Dist: perlin-numpy>=0.0.1
Requires-Dist: pyexr>=0.3.10
Requires-Dist: pytest>=8.3.4
Requires-Dist: tqdm>=4.67.1
